{"nodes":{"30000529":{"name":"MKIG-5","security":-0.221997,"region":"Wicked Creek"},"30000530":{"name":"YHEN-G","security":-0.199527,"region":"Wicked Creek"},"30000531":{"name":"E-JCUS","security":-0.215627,"region":"Wicked Creek"},"30000532":{"name":"W-QN5X","security":-0.272211,"region":"Wicked Creek"},"30000533":{"name":"LP1M-Q","security":-0.243383,"region":"Wicked Creek"},"30000534":{"name":"30-YOU","security":-0.266421,"region":"Wicked Creek"},"30000535":{"name":"384-IN","security":-0.204379,"region":"Wicked Creek"},"30000536":{"name":"4F89-U","security":-0.245349,"region":"Wicked Creek"},"30000537":{"name":"G063-U","security":-0.295999,"region":"Wicked Creek"},"30000538":{"name":"J7-BDX","security":-0.411093,"region":"Wicked Creek"},"30000539":{"name":"MLQ-O9","security":-0.196437,"region":"Wicked Creek"},"30000540":{"name":"L-FM3P","security":-0.170869,"region":"Wicked Creek"},"30000541":{"name":"X-ARMF","security":-0.089626,"region":"Wicked Creek"},"30000542":{"name":"8-OZU1","security":-0.180334,"region":"Wicked Creek"},"30000543":{"name":"0TYR-T","security":-0.155502,"region":"Wicked Creek"},"30000544":{"name":"GM-50Y","security":-0.166767,"region":"Wicked Creek"},"30000545":{"name":"G9L-LP","security":-0.147849,"region":"Wicked Creek"},"30000546":{"name":"MWA-5Q","security":-0.307662,"region":"Wicked Creek"},"30000547":{"name":"H-HHTH","security":-0.421542,"region":"Wicked Creek"},"30000548":{"name":"JQU-KY","security":-0.267341,"region":"Wicked Creek"},"30000549":{"name":"UY5A-D","security":-0.404798,"region":"Wicked Creek"},"30000550":{"name":"C-62I5","security":-0.117561,"region":"Wicked Creek"},"30000551":{"name":"ZH-GKG","security":-0.125268,"region":"Wicked Creek"},"30000552":{"name":"GPLB-C","security":-0.254697,"region":"Wicked Creek"},"30000553":{"name":"GGE-5Q","security":-0.486731,"region":"Wicked Creek"},"30000554":{"name":"5E-CMA","security":-0.420426,"region":"Wicked Creek"},"30000555":{"name":"U104-3","security":-0.266764,"region":"Wicked Creek"},"30000556":{"name":"M3-KAQ","security":-0.315805,"region":"Wicked Creek"},"30000557":{"name":"6-L4YC","security":-0.241496,"region":"Wicked Creek"},"30000558":{"name":"UM-SCG","security":-0.305073,"region":"Wicked Creek"},"30000559":{"name":"F-3FOY","security":-0.412804,"region":"Wicked Creek"},"30000560":{"name":"OAIG-0","security":-0.347397,"region":"Wicked Creek"},"30000561":{"name":"UZ-QXW","security":-0.484818,"region":"Wicked Creek"},"30000562":{"name":"5DE-QS","security":-0.373028,"region":"Wicked Creek"},"30000563":{"name":"R0-DMM","security":-0.46858,"region":"Wicked Creek"},"30000564":{"name":"5Q65-4","security":-0.620508,"region":"Wicked Creek"},"30000565":{"name":"SR-4EK","security":-0.338158,"region":"Wicked Creek"},"30000566":{"name":"0RI-OV","security":-0.294006,"region":"Wicked Creek"},"30000567":{"name":"C-LTXS","security":-0.287824,"region":"Wicked Creek"},"30000568":{"name":"C0O6-K","security":-0.296788,"region":"Wicked Creek"},"30000569":{"name":"HD-AJ7","security":-0.313302,"region":"Wicked Creek"},"30000570":{"name":"G9NE-B","security":-0.329905,"region":"Wicked Creek"},"30000571":{"name":"SJJ-4F","security":-0.246615,"region":"Wicked Creek"},"30000572":{"name":"F-QQ5N","security":-0.650523,"region":"Wicked Creek"},"30000573":{"name":"1-7B6D","security":-0.692394,"region":"Wicked Creek"},"30000574":{"name":"H6-EYX","security":-0.726284,"region":"Wicked Creek"},"30000575":{"name":"U-HVIX","security":-0.661921,"region":"Wicked Creek"},"30000576":{"name":"4-EFLU","security":-0.522806,"region":"Wicked Creek"},"30000577":{"name":"EIH-IU","security":-0.600942,"region":"Wicked Creek"},"30000578":{"name":"F-EM4Q","security":-0.429629,"region":"Wicked Creek"},"30000579":{"name":"1L-OEK","security":-0.66466,"region":"Wicked Creek"},"30000580":{"name":"MN-Q26","security":-0.510912,"region":"Wicked Creek"},"30000581":{"name":"5H-SM2","security":-0.71086,"region":"Wicked Creek"},"30000582":{"name":"4-OS2A","security":-0.595196,"region":"Wicked Creek"},"30000583":{"name":"YI-GV6","security":-0.640814,"region":"Wicked Creek"},"30000584":{"name":"SO-X5L","security":-0.703325,"region":"Wicked Creek"},"30000585":{"name":"XQS-GZ","security":-0.551312,"region":"Wicked Creek"},"30000586":{"name":"Q-GQHN","security":-0.528576,"region":"Wicked Creek"},"30000587":{"name":"A-4JOO","security":-0.196029,"region":"Wicked Creek"},"30000588":{"name":"TP7-KE","security":-0.326929,"region":"Wicked Creek"},"30000589":{"name":"R4N-LD","security":-0.261495,"region":"Wicked Creek"},"30000590":{"name":"3Q-VZA","security":-0.249902,"region":"Wicked Creek"},"30000591":{"name":"M-MBRT","security":-0.239291,"region":"Wicked Creek"},"30000592":{"name":"HPBE-D","security":-0.291605,"region":"Wicked Creek"},"30000593":{"name":"GRHS-B","security":-0.458119,"region":"Wicked Creek"},"30000594":{"name":"J-RXYN","security":-0.458729,"region":"Wicked Creek"},"30000595":{"name":"DUO-51","security":-0.473003,"region":"Wicked Creek"},"30000596":{"name":"07-SLO","security":-0.397503,"region":"Wicked Creek"},"30000597":{"name":"Z-A8FS","security":-0.542356,"region":"Wicked Creek"},"30000598":{"name":"GPD5-0","security":-0.305684,"region":"Wicked Creek"},"30000599":{"name":"LKZ-CY","security":-0.449541,"region":"Wicked Creek"},"30000600":{"name":"F5M-CC","security":-0.386747,"region":"Wicked Creek"},"30000601":{"name":"TZE-UB","security":-0.32393,"region":"Wicked Creek"},"30000602":{"name":"WRL4-2","security":-0.409574,"region":"Wicked Creek"},"30000603":{"name":"V7G-RL","security":-0.441294,"region":"Wicked Creek"},"30000604":{"name":"XEN7-0","security":-0.186493,"region":"Wicked Creek"},"30000605":{"name":"L-Z9KJ","security":-0.346744,"region":"Wicked Creek"},"30000606":{"name":"7K-NSE","security":-0.28626,"region":"Wicked Creek"},"30000607":{"name":"OR-7N5","security":-0.298069,"region":"Wicked Creek"},"30000608":{"name":"JEQG-7","security":-0.286209,"region":"Wicked Creek"},"30000609":{"name":"5NQI-E","security":-0.249721,"region":"Wicked Creek"},"30000610":{"name":"B-WQDP","security":-0.342153,"region":"Wicked Creek"}},"edges":[{"from":30000529,"to":30000530},{"from":30000529,"to":30000534},{"from":30000529,"to":30000544},{"from":30000529,"to":30000557},{"from":30000530,"to":30000529},{"from":30000530,"to":30000531},{"from":30000530,"to":30000534},{"from":30000530,"to":30000535},{"from":30000531,"to":30000530},{"from":30000531,"to":30000532},{"from":30000531,"to":30000533},{"from":30000531,"to":30000536},{"from":30000532,"to":30000531},{"from":30000532,"to":30000537},{"from":30000533,"to":30000531},{"from":30000533,"to":30000598},{"from":30000534,"to":30000529},{"from":30000534,"to":30000530},{"from":30000534,"to":30000536},{"from":30000534,"to":30000538},{"from":30000535,"to":30000530},{"from":30000535,"to":30000557},{"from":30000536,"to":30000531},{"from":30000536,"to":30000534},{"from":30000536,"to":30000557},{"from":30000537,"to":30000532},{"from":30000537,"to":30000596},{"from":30000538,"to":30000534},{"from":30000539,"to":30000542},{"from":30000540,"to":30000543},{"from":30000540,"to":30000544},{"from":30000541,"to":30000545},{"from":30000542,"to":30000539},{"from":30000542,"to":30000543},{"from":30000543,"to":30000540},{"from":30000543,"to":30000542},{"from":30000544,"to":30000529},{"from":30000544,"to":30000540},{"from":30000544,"to":30000545},{"from":30000545,"to":30000541},{"from":30000545,"to":30000544},{"from":30000546,"to":30000547},{"from":30000546,"to":30000548},{"from":30000546,"to":30000549},{"from":30000546,"to":30000558},{"from":30000547,"to":30000546},{"from":30000547,"to":30000549},{"from":30000547,"to":30000600},{"from":30000548,"to":30000546},{"from":30000548,"to":30000550},{"from":30000549,"to":30000546},{"from":30000549,"to":30000547},{"from":30000549,"to":30000551},{"from":30000550,"to":30000548},{"from":30000550,"to":30000551},{"from":30000551,"to":30000549},{"from":30000551,"to":30000550},{"from":30000552,"to":30000554},{"from":30000552,"to":30000555},{"from":30000552,"to":30000557},{"from":30000553,"to":30000554},{"from":30000553,"to":30000562},{"from":30000554,"to":30000552},{"from":30000554,"to":30000553},{"from":30000554,"to":30000610},{"from":30000555,"to":30000552},{"from":30000555,"to":30000556},{"from":30000556,"to":30000555},{"from":30000556,"to":30000594},{"from":30000557,"to":30000529},{"from":30000557,"to":30000535},{"from":30000557,"to":30000536},{"from":30000557,"to":30000552},{"from":30000558,"to":30000546},{"from":30000558,"to":30000560},{"from":30000558,"to":30000588},{"from":30000559,"to":30000562},{"from":30000559,"to":30000593},{"from":30000560,"to":30000558},{"from":30000560,"to":30000562},{"from":30000561,"to":30000562},{"from":30000561,"to":30000563},{"from":30000562,"to":30000553},{"from":30000562,"to":30000559},{"from":30000562,"to":30000560},{"from":30000562,"to":30000561},{"from":30000563,"to":30000561},{"from":30000563,"to":30000564},{"from":30000564,"to":30000563},{"from":30000565,"to":30000566},{"from":30000565,"to":30000568},{"from":30000565,"to":30000569},{"from":30000565,"to":30000570},{"from":30000566,"to":30000565},{"from":30000566,"to":30000568},{"from":30000566,"to":30000570},{"from":30000566,"to":30000605},{"from":30000567,"to":30000568},{"from":30000567,"to":30000569},{"from":30000567,"to":30000571},{"from":30000568,"to":30000565},{"from":30000568,"to":30000566},{"from":30000568,"to":30000567},{"from":30000568,"to":30000569},{"from":30000568,"to":30000570},{"from":30000569,"to":30000565},{"from":30000569,"to":30000567},{"from":30000569,"to":30000568},{"from":30000569,"to":30000571},{"from":30000570,"to":30000565},{"from":30000570,"to":30000566},{"from":30000570,"to":30000568},{"from":30000571,"to":30000567},{"from":30000571,"to":30000569},{"from":30000572,"to":30000573},{"from":30000572,"to":30000575},{"from":30000572,"to":30000576},{"from":30000572,"to":30000579},{"from":30000573,"to":30000572},{"from":30000573,"to":30000574},{"from":30000573,"to":30000576},{"from":30000574,"to":30000573},{"from":30000575,"to":30000572},{"from":30000575,"to":30000576},{"from":30000575,"to":30000577},{"from":30000576,"to":30000572},{"from":30000576,"to":30000573},{"from":30000576,"to":30000575},{"from":30000577,"to":30000575},{"from":30000578,"to":30000580},{"from":30000579,"to":30000572},{"from":30000579,"to":30000581},{"from":30000579,"to":30000583},{"from":30000579,"to":30000584},{"from":30000579,"to":30000586},{"from":30000580,"to":30000578},{"from":30000580,"to":30000582},{"from":30000580,"to":30000585},{"from":30000580,"to":30000586},{"from":30000581,"to":30000579},{"from":30000582,"to":30000580},{"from":30000582,"to":30000586},{"from":30000583,"to":30000579},{"from":30000583,"to":30000584},{"from":30000584,"to":30000579},{"from":30000584,"to":30000583},{"from":30000585,"to":30000580},{"from":30000585,"to":30000586},{"from":30000585,"to":30000599},{"from":30000586,"to":30000579},{"from":30000586,"to":30000580},{"from":30000586,"to":30000582},{"from":30000586,"to":30000585},{"from":30000587,"to":30000588},{"from":30000587,"to":30000590},{"from":30000588,"to":30000558},{"from":30000588,"to":30000587},{"from":30000588,"to":30000589},{"from":30000589,"to":30000588},{"from":30000589,"to":30000591},{"from":30000589,"to":30000592},{"from":30000590,"to":30000587},{"from":30000591,"to":30000589},{"from":30000592,"to":30000589},{"from":30000593,"to":30000559},{"from":30000593,"to":30000594},{"from":30000593,"to":30000595},{"from":30000594,"to":30000556},{"from":30000594,"to":30000593},{"from":30000594,"to":30000595},{"from":30000594,"to":30000597},{"from":30000595,"to":30000593},{"from":30000595,"to":30000594},{"from":30000595,"to":30000596},{"from":30000595,"to":30000597},{"from":30000596,"to":30000537},{"from":30000596,"to":30000595},{"from":30000596,"to":30000597},{"from":30000596,"to":30000598},{"from":30000597,"to":30000594},{"from":30000597,"to":30000595},{"from":30000597,"to":30000596},{"from":30000598,"to":30000533},{"from":30000598,"to":30000596},{"from":30000599,"to":30000585},{"from":30000599,"to":30000600},{"from":30000599,"to":30000602},{"from":30000600,"to":30000547},{"from":30000600,"to":30000599},{"from":30000600,"to":30000601},{"from":30000601,"to":30000600},{"from":30000601,"to":30000604},{"from":30000602,"to":30000599},{"from":30000602,"to":30000603},{"from":30000603,"to":30000602},{"from":30000604,"to":30000601},{"from":30000605,"to":30000566},{"from":30000605,"to":30000606},{"from":30000606,"to":30000605},{"from":30000606,"to":30000607},{"from":30000607,"to":30000606},{"from":30000607,"to":30000608},{"from":30000607,"to":30000609},{"from":30000608,"to":30000607},{"from":30000608,"to":30000610},{"from":30000609,"to":30000607},{"from":30000610,"to":30000554},{"from":30000610,"to":30000608}]}
